corsikaio/__init__.py
corsikaio/_version.py
corsikaio/constants.py
corsikaio/file.py
corsikaio/io.py
corsikaio/longitudinal.py
corsikaio/version.py
corsikaio/subblocks/__init__.py
corsikaio/subblocks/data.py
corsikaio/subblocks/dtypes.py
corsikaio/subblocks/event_end.py
corsikaio/subblocks/event_header.py
corsikaio/subblocks/longitudinal.py
corsikaio/subblocks/run_end.py
corsikaio/subblocks/run_header.py
corsikaio-0.6.1.dist-info/licenses/LICENSE
corsikaio-0.6.1.dist-info/METADATA
corsikaio-0.6.1.dist-info/WHEEL
corsikaio-0.6.1.dist-info/top_level.txt
corsikaio-0.6.1.dist-info/RECORD
