Metadata-Version: 2.4
Name: corsikaio
Version: 0.6.1
Summary: Reader for corsika binary output files using numpy
Maintainer-email: Maximilian Linhoff <maximilian.linhoff@cta-observatory.org>
License-Expression: MIT
Project-URL: Homepage, http://github.com/cta-observatory/pycorsikaio
Requires-Python: >=3.11
License-File: LICENSE
Requires-Dist: numpy
Provides-Extra: dev
Requires-Dist: setuptools_scm[toml]; extra == "dev"
Provides-Extra: zstd
Requires-Dist: zstandard; extra == "zstd"
Provides-Extra: tests
Requires-Dist: pytest; extra == "tests"
Requires-Dist: scipy; extra == "tests"
Provides-Extra: all
Requires-Dist: corsikaio[tests,zstd]; extra == "all"
Dynamic: license-file
